{"upstream-server": "http://localhost:9999", "resources": {"GET-200-products/__id": {"category": "Product", "upstream-server": true}, "GET-200-user/__id": {"category": "User"}, "DELETE-404-user/kevin": {"category": "User", "upstream-server": false}, "GET-200-user/john": {"category": "User"}, "GET-200-user/tom": {"category": "User"}, "POST-200-event": {"category": "Event", "upstream-server": true}, "GET-200-user/__id/family/__name": {"category": "User"}, "RPC-user.list": {"upstream-server": false}, "POST-200-user": {"category": "User"}}}